README.md
setup.cfg
setup.py
gaus_bino_distros/Binomialdistribution.py
gaus_bino_distros/Gaussiandistribution.py
gaus_bino_distros/Generaldistribution.py
gaus_bino_distros/__init__.py
gaus_bino_distros.egg-info/PKG-INFO
gaus_bino_distros.egg-info/SOURCES.txt
gaus_bino_distros.egg-info/dependency_links.txt
gaus_bino_distros.egg-info/not-zip-safe
gaus_bino_distros.egg-info/top_level.txt